termcast.py
termcast-0.1a18.dist-info/METADATA
termcast-0.1a18.dist-info/WHEEL
termcast-0.1a18.dist-info/entry_points.txt
termcast-0.1a18.dist-info/top_level.txt
termcast-0.1a18.dist-info/RECORD
