Metadata-Version: 2.1
Name: termcast
Version: 0.1a18
Summary: A tool to share the contents of your terminal over the web
Home-page: https://github.com/lampholder/termcast
Author: Thomas Lant
Author-email: lampholder@gmail.com
License: MIT
Keywords: terminal screencast
Platform: UNKNOWN
Classifier: Development Status :: 3 - Alpha
Classifier: Intended Audience :: Developers
Classifier: Intended Audience :: Education
Classifier: Intended Audience :: System Administrators
Classifier: License :: OSI Approved :: MIT License
Classifier: Programming Language :: Python :: 2.7
Classifier: Programming Language :: Python :: 3
Classifier: Programming Language :: Python :: 3.0
Classifier: Programming Language :: Python :: 3.1
Classifier: Programming Language :: Python :: 3.2
Classifier: Programming Language :: Python :: 3.3
Classifier: Programming Language :: Python :: 3.4
Classifier: Programming Language :: Python :: 3.5
Classifier: Programming Language :: Python :: 3.6
Classifier: Programming Language :: Python :: 3.7
Requires-Python: >=2.7.9
Requires-Dist: requests
Requires-Dist: websocket-client
